mctech_core/__init__.py
mctech_core/testmain.py
mctech_core/config/__init__.py
mctech_core/config/_configure.py
mctech_core/config/config_merger.py
mctech_core/config/config_value.py
mctech_core/config/yaml_loader.py
mctech_core/context/__init__.py
mctech_core/context/async_context.py
mctech_core/context/header_filter.py
mctech_core-1.1.4.dist-info/METADATA
mctech_core-1.1.4.dist-info/WHEEL
mctech_core-1.1.4.dist-info/top_level.txt
mctech_core-1.1.4.dist-info/RECORD
