Metadata-Version: 2.1
Name: mctech-core
Version: 1.1.4
Summary: UNKNOWN
Home-page: UNKNOWN
License: UNKNOWN
Platform: UNKNOWN
Requires-Dist: log4py
Requires-Dist: pyyaml
Requires-Dist: pyDes
